my_robot_sdk/__init__.py
my_robot_sdk/client.py
my_robot_sdk-0.1.0.dist-info/METADATA
my_robot_sdk-0.1.0.dist-info/WHEEL
my_robot_sdk-0.1.0.dist-info/RECORD
